spectfm/__init__.py
spectfm/_modidx.py
spectfm/core.py
spectfm/visualization.py
spectfm-0.0.1.dist-info/LICENSE
spectfm-0.0.1.dist-info/METADATA
spectfm-0.0.1.dist-info/WHEEL
spectfm-0.0.1.dist-info/entry_points.txt
spectfm-0.0.1.dist-info/top_level.txt
spectfm-0.0.1.dist-info/RECORD
